{
  "type": "minecraft:chest",
  "pools": [
    {
      "rolls": 9,
      "entries": [
        {
          "type": "minecraft:item",
          "name": "minecraft:netherite_ingot",
          "conditions": [
            {
              "condition": "minecraft:random_chance",
              "chance": 0.02
            }
          ]
        }
      ],
      "functions": [
        {
          "function": "minecraft:limit_count",
          "limit": 1
        }
      ]
    },
    {
      "rolls": 9,
      "entries": [
        {
          "type": "minecraft:item",
          "name": "minecraft:diamond",
          "conditions": [
            {
              "condition": "minecraft:random_chance",
              "chance": 0.13
            }
          ]
        }
      ],
      "functions": [
        {
          "function": "minecraft:limit_count",
          "limit": {
            "min": 2,
            "max": 4
          }
        }
      ]
    },
    {
      "rolls": 9,
      "entries": [
        {
          "type": "minecraft:item",
          "name": "minecraft:netherite_upgrade_smithing_template",
          "conditions": [
            {
              "condition": "minecraft:random_chance",
              "chance": 0.05
            }
          ]
        }
      ],
      "functions": [
        {
          "function": "minecraft:limit_count",
          "limit": {
            "min": 1,
            "max": 2
          }
        }
      ]
    },
    {
      "rolls": 9,
      "entries": [
        {
          "type": "minecraft:item",
          "name": "minecraft:enchanted_golden_apple",
          "conditions": [
            {
              "condition": "minecraft:random_chance",
              "chance": 0.005
            }
          ]
        }
      ],
      "functions": [
        {
          "function": "minecraft:limit_count",
          "limit": 1
        }
      ]
    },
    {
      "rolls": 9,
      "entries": [
        {
          "type": "minecraft:item",
          "name": "minecraft:nether_star",
          "conditions": [
            {
              "condition": "minecraft:random_chance",
              "chance": 0.01
            }
          ]
        }
      ],
      "functions": [
        {
          "function": "minecraft:limit_count",
          "limit": 1
        }
      ]
    },
    {
      "rolls": 9,
      "entries": [
        {
          "type": "minecraft:item",
          "name": "minecraft:wither_skeleton_skull",
          "conditions": [
            {
              "condition": "minecraft:random_chance",
              "chance": 0.06
            }
          ]
        }
      ],
      "functions": [
        {
          "function": "minecraft:limit_count",
          "limit": {
            "min": 2,
            "max": 6
          }
        }
      ]
    },
    {
      "rolls": 9,
      "entries": [
        {
          "type": "minecraft:item",
          "name": "minecraft:iron_block",
          "conditions": [
            {
              "condition": "minecraft:random_chance",
              "chance": 0.08
            }
          ]
        }
      ],
      "functions": [
        {
          "function": "minecraft:limit_count",
          "limit": {
            "min": 2,
            "max": 5
          }
        }
      ]
    },
    {
      "rolls": 9,
      "entries": [
        {
          "type": "minecraft:item",
          "name": "minecraft:diamond_block",
          "conditions": [
            {
              "condition": "minecraft:random_chance",
              "chance": 0.05
            }
          ]
        }
      ],
      "functions": [
        {
          "function": "minecraft:limit_count",
          "limit": 1
        }
      ]
    },
    {
      "rolls": 9,
      "entries": [
        {
          "type": "minecraft:item",
          "name": "minecraft:ancient_debris",
          "conditions": [
            {
              "condition": "minecraft:random_chance",
              "chance": 0.08
            }
          ]
        }
      ],
      "functions": [
        {
          "function": "minecraft:limit_count",
          "limit": 1
        }
      ]
    },
    {
      "rolls": 9,
      "entries": [
        {
          "type": "minecraft:item",
          "name": "minecraft:gold_block",
          "conditions": [
            {
              "condition": "minecraft:random_chance",
              "chance": 0.06
            }
          ]
        }
      ],
      "functions": [
        {
          "function": "minecraft:limit_count",
          "limit": {
            "min": 2,
            "max": 6
          }
        }
      ]
    },
    {
      "rolls": 9,
      "entries": [
        {
          "type": "minecraft:item",
          "name": "minecraft:iron_ingot",
          "conditions": [
            {
              "condition": "minecraft:random_chance",
              "chance": 0.09
            }
          ]
        }
      ],
      "functions": [
        {
          "function": "minecraft:limit_count",
          "limit": {
            "min": 6,
            "max": 12
          }
        }
      ]
    },
    {
      "rolls": 9,
      "entries": [
        {
          "type": "minecraft:item",
          "name": "minecraft:gold_ingot",
          "conditions": [
            {
              "condition": "minecraft:random_chance",
              "chance": 0.165
            }
          ]
        }
      ],
      "functions": [
        {
          "function": "minecraft:limit_count",
          "limit": {
            "min": 4,
            "max": 10
          }
        }
      ]
    },
    {
      "rolls": {
        "type": "minecraft:binomial",
        "n": 1,
        "p": 0.0025
      },
      "entries": [
        {
          "type": "minecraft:item",
          "name": "minecraft:leather_boots",
          "functions": [
            {
              "function": "minecraft:set_nbt",
              "tag": "{Damage:0,Trim:{material:\"minecraft:gold\",pattern:\"minecraft:spire\"},display:{Lore:['{\"text\":\"\",\"extra\":[{\"text\":\"Lost Labyrinth of Ptah\",\"italic\":false,\"color\":\"gray\"}]}','{\"text\":\"Boots of a royal guardsman\",\"italic\":false}'],Name:'{\"extra\":[{\"italic\":false,\"color\":\"yellow\",\"text\":\"Royal Guard Boots\"}],\"text\":\"\"}',color:16711680}}"
            }
          ]
        }
      ]
    },
    {
      "rolls": {
        "type": "minecraft:binomial",
        "n": 1,
        "p": 0.0025
      },
      "entries": [
        {
          "type": "minecraft:item",
          "name": "minecraft:chainmail_leggings",
          "functions": [
            {
              "function": "minecraft:set_nbt",
              "tag": "{Damage:0,Trim:{material:\"minecraft:gold\",pattern:\"minecraft:wild\"},display:{Lore:['{\"text\":\"\",\"extra\":[{\"text\":\"Lost Labyrinth of Ptah\",\"italic\":false,\"color\":\"gray\"}]}','{\"text\":\"Leggings of a royal guardsman\",\"italic\":false}'],Name:'{\"extra\":[{\"italic\":false,\"color\":\"yellow\",\"text\":\"Royal Guard Leggings\"}],\"text\":\"\"}'}}"
            }
          ]
        }
      ]
    },
    {
      "rolls": {
        "type": "minecraft:binomial",
        "n": 1,
        "p": 0.0025
      },
      "entries": [
        {
          "type": "minecraft:item",
          "name": "minecraft:leather_chestplate",
          "functions": [
            {
              "function": "minecraft:set_nbt",
              "tag": "{Damage:0,Trim:{material:\"minecraft:gold\",pattern:\"minecraft:sentry\"},display:{Lore:['{\"text\":\"\",\"extra\":[{\"text\":\"Lost Labyrinth of Ptah\",\"italic\":false,\"color\":\"gray\"}]}','{\"text\":\"Chestplate of a royal guardsman\",\"italic\":false}'],Name:'{\"text\":\"Royal Guard Chestplate\",\"color\":\"yellow\",\"italic\":false}',color:16711680}}"
            }
          ]
        }
      ]
    },
    {
      "rolls": {
        "type": "minecraft:binomial",
        "n": 1,
        "p": 0.0025
      },
      "entries": [
        {
          "type": "minecraft:item",
          "name": "minecraft:chainmail_helmet",
          "functions": [
            {
              "function": "minecraft:set_nbt",
              "tag": "{Damage:0,Trim:{material:\"minecraft:gold\",pattern:\"minecraft:silence\"},display:{Lore:['{\"text\":\"\",\"extra\":[{\"text\":\"Lost Labyrinth of Ptah\",\"italic\":false,\"color\":\"gray\"}]}','{\"text\":\"Helmet of a royal guardsman\",\"italic\":false}'],Name:'{\"text\":\"Royal Guard Helmet\",\"color\":\"yellow\",\"italic\":false}'}}"
            }
          ]
        }
      ]
    }
  ]
}
